{
  "name":"inquiry",
  "ns":"json",
  "description":"Inquiry is a JSON path language that supports parameters, JavaScript expressions, and sub-queries",
  "ports":{
    "input":{
      "path":{
        "type":"object",
        "title":"JSON object",
        "description":"Accepts a generic JSON object as input",
        "readonly": true
      },
      "json":{
        "type":"object",
        "title":"JSON object",
        "description":"Accepts a generic JSON object as input",
        "readonly": true
      }
    },
    "output":{}
  }
}
